odoo10_addon_account_invoice_change_currency-10.0.1.0.0.99.dev5-py2.7-nspkg.pth
odoo/addons/account_invoice_change_currency/README.rst
odoo/addons/account_invoice_change_currency/__init__.py
odoo/addons/account_invoice_change_currency/__manifest__.py
odoo/addons/account_invoice_change_currency/i18n/account_invoice_change_currency.pot
odoo/addons/account_invoice_change_currency/static/description/icon.png
odoo/addons/account_invoice_change_currency/tests/__init__.py
odoo/addons/account_invoice_change_currency/tests/test_account_invoice_change_currency.py
odoo/addons/account_invoice_change_currency/views/account_invoice.xml
odoo/addons/account_invoice_change_currency/wizard/__init__.py
odoo/addons/account_invoice_change_currency/wizard/wizard_change_invoice_currency.py
odoo/addons/account_invoice_change_currency/wizard/wizard_change_invoice_currency.xml
odoo10_addon_account_invoice_change_currency-10.0.1.0.0.99.dev5.dist-info/METADATA
odoo10_addon_account_invoice_change_currency-10.0.1.0.0.99.dev5.dist-info/RECORD
odoo10_addon_account_invoice_change_currency-10.0.1.0.0.99.dev5.dist-info/WHEEL
odoo10_addon_account_invoice_change_currency-10.0.1.0.0.99.dev5.dist-info/namespace_packages.txt
odoo10_addon_account_invoice_change_currency-10.0.1.0.0.99.dev5.dist-info/top_level.txt
